trank/__init__.py
trank/service.py
trank/trank.py
trank/static/logo.png
trank/templates/hello.jade
trank/templates/layout.jade
trank-0.1.0.data/scripts/trank_start
trank-0.1.0.dist-info/AUTHORS
trank-0.1.0.dist-info/LICENSE
trank-0.1.0.dist-info/METADATA
trank-0.1.0.dist-info/WHEEL
trank-0.1.0.dist-info/top_level.txt
trank-0.1.0.dist-info/RECORD
