Metadata-Version: 2.1
Name: trank
Version: 0.1.0
Summary: A web based application to rank tennis players
Home-page: https://bitbucket.org/grupoinvestigativodesistemas/trank
Author: Grupo Investigativo de Sistemas
License: UNKNOWN
Project-URL: Bug Reports, https://bitbucket.org/grupoinvestigativodesistemas/trank/issues
Platform: UNKNOWN
Classifier: Programming Language :: Python :: 3
Classifier: License :: OSI Approved :: BSD License
Classifier: Operating System :: OS Independent
Requires-Python: >= 3.7.4
Requires-Dist: psycopg2 (==2.8.*)
Requires-Dist: pycrypto (==2.6.*)
Requires-Dist: flask (==1.0.*)
Requires-Dist: pyjade (==4.0.*)
Requires-Dist: queuepool (==1.3.*)
Requires-Dist: pyaconf (==0.7.*)
Requires-Dist: pyyaml (==5.1.*)
